livekit/plugins/spitch/__init__.py
livekit/plugins/spitch/log.py
livekit/plugins/spitch/py.typed
livekit/plugins/spitch/stt.py
livekit/plugins/spitch/tts.py
livekit/plugins/spitch/version.py
livekit_plugins_spitch-1.3.11.dist-info/METADATA
livekit_plugins_spitch-1.3.11.dist-info/WHEEL
livekit_plugins_spitch-1.3.11.dist-info/RECORD
